deepl_fastapi/__init__.py
deepl_fastapi/__main__.py
deepl_fastapi/deepl_server.py
deepl_fastapi/deepl_server.py.portalocker.lock
deepl_fastapi/run_uvicorn.py
deepl_fastapi-0.1.2.dist-info/entry_points.txt
deepl_fastapi-0.1.2.dist-info/LICENSE
deepl_fastapi-0.1.2.dist-info/WHEEL
deepl_fastapi-0.1.2.dist-info/METADATA
deepl_fastapi-0.1.2.dist-info/RECORD
