Metadata-Version: 2.1
Name: deepl-fastapi
Version: 0.1.2
Summary: deepl via fastapi
Home-page: https://github.com/ffreemt/deepl-fastapi
License: MIT
Author: freemt
Requires-Python: >=3.7,<4.0
Classifier: License :: OSI Approved :: MIT License
Classifier: Programming Language :: Python :: 3
Classifier: Programming Language :: Python :: 3.7
Classifier: Programming Language :: Python :: 3.8
Classifier: Programming Language :: Python :: 3.9
Classifier: Programming Language :: Python :: 3.10
Requires-Dist: deepl-scraper-pp (>=0.1.2,<0.2.0)
Requires-Dist: fastapi (>=0.63.0,<0.64.0)
Requires-Dist: get-ppbrowser (>=0.1.3,<0.2.0)
Requires-Dist: logzero (>=1.6.3,<2.0.0)
Requires-Dist: nest-asyncio (>=1.5.1,<2.0.0)
Requires-Dist: portalocker (>=2.2.1,<3.0.0)
Requires-Dist: requests (>=2.25.1,<3.0.0)
Requires-Dist: uvicorn (>=0.13.4,<0.14.0)
Project-URL: Repository, https://github.com/ffreemt/deepl-fastapi
